pysurfacefit/__init__.py
pysurfacefit/command_line.py
pysurfacefit/tasks.py
pysurfacefit/config/__init__.py
pysurfacefit/config/base.py
pysurfacefit/config/templates/__init__.py
pysurfacefit/config/templates/calc.py
pysurfacefit/config/templates/codegen.py
pysurfacefit/config/templates/data.py
pysurfacefit/config/templates/fit.py
pysurfacefit/config/templates/general.py
pysurfacefit/config/templates/model.py
pysurfacefit/config/templates/plotting.py
pysurfacefit/config/templates/stat.py
pysurfacefit/data/__init__.py
pysurfacefit/data/datagroups.py
pysurfacefit/fitpars/__init__.py
pysurfacefit/fitpars/pars.py
pysurfacefit/fitpars/pars_collect.py
pysurfacefit/fitpars/pars_old.py
pysurfacefit/fitter/__init__.py
pysurfacefit/fitter/base.py
pysurfacefit/fitter/fitter.py
pysurfacefit/formats/__init__.py
pysurfacefit/formats/dill/__init__.py
pysurfacefit/formats/dill/default.py
pysurfacefit/formats/fixcol/__init__.py
pysurfacefit/formats/json/__init__.py
pysurfacefit/grids/__init__.py
pysurfacefit/grids/base.py
pysurfacefit/grids/grids.py
pysurfacefit/models/__init__.py
pysurfacefit/models/base.py
pysurfacefit/models/fitmodels.py
pysurfacefit/models/fortran.py
pysurfacefit/models/library.py
pysurfacefit/models/sympy.py
pysurfacefit-0.1.dist-info/LICENSE.md
pysurfacefit-0.1.dist-info/METADATA
pysurfacefit-0.1.dist-info/WHEEL
pysurfacefit-0.1.dist-info/entry_points.txt
pysurfacefit-0.1.dist-info/top_level.txt
pysurfacefit-0.1.dist-info/RECORD
